README.md
setup.cfg
setup.py
performer/__init__.py
performer/benchmark.py
performer/color.py
performer/formatter.py
performer.egg-info/PKG-INFO
performer.egg-info/SOURCES.txt
performer.egg-info/dependency_links.txt
performer.egg-info/top_level.txt