Metadata-Version: 2.1
Name: performer
Version: 0.0.1
Summary: Lightweight benchmarking decorator.
Home-page: https://github.com/KeisukeToyota/performer
Author: KeisukeToyota
Author-email: hm.pudding0715@gmail.com
Maintainer: KeisukeToyota
Maintainer-email: hm.pudding0715@gmail.com
License: MIT
Platform: UNKNOWN
